pybandiger/PyBandiger.py
pybandiger/__init__.py
pybandiger-0.1.9.dist-info/LICENSE
pybandiger-0.1.9.dist-info/METADATA
pybandiger-0.1.9.dist-info/WHEEL
pybandiger-0.1.9.dist-info/top_level.txt
pybandiger-0.1.9.dist-info/RECORD
