Metadata-Version: 2.1
Name: pybandiger
Version: 0.1.9
Summary: A data wrangling library
Home-page: https://github.com/LansariFedi/PyBandiger
Author: Lansari Fedi
Author-email: lansarifedi7@gmail.com
License: UNKNOWN
Platform: UNKNOWN
Classifier: Programming Language :: Python :: 3
Classifier: License :: OSI Approved :: MIT License
Classifier: Operating System :: OS Independent
Requires-Python: >=3.6
License-File: LICENSE
Requires-Dist: scikit-learn
Requires-Dist: pandas
